<?xml version="1.0" ?>
<!DOCTYPE PubmedArticleSet PUBLIC "-//NLM//DTD PubMedArticle, 1st January 2024//EN" "https://dtd.nlm.nih.gov/ncbi/pubmed/out/pubmed_240101.dtd">
<PubmedArticleSet>
<PubmedArticle><MedlineCitation Status="MEDLINE" Owner="NLM"><PMID Version="1">18419017</PMID><DateCompleted><Year>2008</Year><Month>07</Month><Day>17</Day></DateCompleted><DateRevised><Year>2019</Year><Month>09</Month><Day>23</Day></DateRevised><Article PubModel="Print"><Journal><ISSN IssnType="Print">1061-4303</ISSN><JournalIssue CitedMedium="Print"><Volume>80</Volume><Issue>3</Issue><PubDate><Year>2008</Year><Month>Mar</Month></PubDate></JournalIssue><Title>Water environment research : a research publication of the Water Environment Federation</Title><ISOAbbreviation>Water Environ Res</ISOAbbreviation></Journal><ArticleTitle>Concentration and recovery of coliphages from water with bituminous coal.</ArticleTitle><Pagination><StartPage>282</StartPage><EndPage>288</EndPage><MedlinePgn>282-8</MedlinePgn></Pagination><Abstract><AbstractText>Coliphages represent a process indicator for fecal pollution. The coal bed concentration method prepared for enterovirus was refined for a concentration of coliphages. A bed made from 1.5 g of 120-mesh coal powder was used for concentrating coliphage from 200 mL of a water sample with or without the addition of aluminum chloride at different pH values. The isolated E. coli strain EC-R8 was found to be more susceptible to the desired coliphage and showed significant coliphage-coliform response, with clear plaque used for further studies. The complete coliphage adsorption was achieved with the addition of 0.0005 M AlCl3 at pH 6.0. Adsorbed coliphages were eluted with 3% beef extract in Mcllvaine buffer at pH 7.1, with an average recovery of 78.74%. This concentration technique was applied for the detection of coliphages from the well water of Nagpur city (India) and found to contain coliphages in the range of 2 to 28 plaque-forming units per liter (PFU/L).</AbstractText></Abstract><AuthorList CompleteYN="Y"><Author ValidYN="Y"><LastName>Dafale</LastName><ForeName>Nishant</ForeName><Initials>N</Initials><AffiliationInfo><Affiliation>National Environmental Engineering Research Institute, Nagpur, India.</Affiliation></AffiliationInfo></Author><Author ValidYN="Y"><LastName>Lakhe</LastName><ForeName>Shrikumar</ForeName><Initials>S</Initials></Author><Author ValidYN="Y"><LastName>Yadav</LastName><ForeName>Krishnakant</ForeName><Initials>K</Initials></Author><Author ValidYN="Y"><LastName>Purohit</LastName><ForeName>Hemant</ForeName><Initials>H</Initials></Author><Author ValidYN="Y"><LastName>Chakrabarti</LastName><ForeName>Tapan</ForeName><Initials>T</Initials></Author></AuthorList><Language>eng</Language><PublicationTypeList><PublicationType UI="D016428">Journal Article</PublicationType></PublicationTypeList></Article><MedlineJournalInfo><Country>United States</Country><MedlineTA>Water Environ Res</MedlineTA><NlmUniqueID>9886167</NlmUniqueID><ISSNLinking>1061-4303</ISSNLinking></MedlineJournalInfo><ChemicalList><Chemical><RegistryNumber>0</RegistryNumber><NameOfSubstance UI="D003031">Coal</NameOfSubstance></Chemical></ChemicalList><CitationSubset>IM</CitationSubset><MeshHeadingList><MeshHeading><DescriptorName UI="D000327" MajorTopicYN="N">Adsorption</DescriptorName></MeshHeading><MeshHeading><DescriptorName UI="D003031" MajorTopicYN="Y">Coal</DescriptorName></MeshHeading><MeshHeading><DescriptorName UI="D003090" MajorTopicYN="N">Coliphages</DescriptorName><QualifierName UI="Q000302" MajorTopicYN="Y">isolation &amp; purification</QualifierName></MeshHeading><MeshHeading><DescriptorName UI="D005374" MajorTopicYN="N">Filtration</DescriptorName><QualifierName UI="Q000379" MajorTopicYN="Y">methods</QualifierName></MeshHeading><MeshHeading><DescriptorName UI="D006801" MajorTopicYN="N">Humans</DescriptorName></MeshHeading><MeshHeading><DescriptorName UI="D014876" MajorTopicYN="N">Water Pollution</DescriptorName><QualifierName UI="Q000032" MajorTopicYN="Y">analysis</QualifierName></MeshHeading><MeshHeading><DescriptorName UI="D018508" MajorTopicYN="N">Water Purification</DescriptorName><QualifierName UI="Q000379" MajorTopicYN="N">methods</QualifierName></MeshHeading><MeshHeading><DescriptorName UI="D014881" MajorTopicYN="N">Water Supply</DescriptorName><QualifierName UI="Q000032" MajorTopicYN="N">analysis</QualifierName></MeshHeading></MeshHeadingList></MedlineCitation><PubmedData><History><PubMedPubDate PubStatus="pubmed"><Year>2008</Year><Month>4</Month><Day>19</Day><Hour>9</Hour><Minute>0</Minute></PubMedPubDate><PubMedPubDate PubStatus="medline"><Year>2008</Year><Month>7</Month><Day>18</Day><Hour>9</Hour><Minute>0</Minute></PubMedPubDate><PubMedPubDate PubStatus="entrez"><Year>2008</Year><Month>4</Month><Day>19</Day><Hour>9</Hour><Minute>0</Minute></PubMedPubDate></History><PublicationStatus>ppublish</PublicationStatus><ArticleIdList><ArticleId IdType="pubmed">18419017</ArticleId><ArticleId IdType="doi">10.2175/106143007x220923</ArticleId></ArticleIdList></PubmedData></PubmedArticle></PubmedArticleSet>