<?xml version="1.0" ?>
<!DOCTYPE PubmedArticleSet PUBLIC "-//NLM//DTD PubMedArticle, 1st January 2024//EN" "https://dtd.nlm.nih.gov/ncbi/pubmed/out/pubmed_240101.dtd">
<PubmedArticleSet>
<PubmedArticle><MedlineCitation Status="MEDLINE" Owner="NLM"><PMID Version="1">1967100</PMID><DateCompleted><Year>1993</Year><Month>04</Month><Day>22</Day></DateCompleted><DateRevised><Year>2006</Year><Month>11</Month><Day>15</Day></DateRevised><Article PubModel="Print"><Journal><ISSN IssnType="Print">0213-005X</ISSN><JournalIssue CitedMedium="Print"><Volume>8</Volume><Issue>7</Issue><PubDate><Year>1990</Year><Season>Aug-Sep</Season></PubDate></JournalIssue><Title>Enfermedades infecciosas y microbiologia clinica</Title><ISOAbbreviation>Enferm Infecc Microbiol Clin</ISOAbbreviation></Journal><ArticleTitle>[Viral infections associated with intestinal invagination].</ArticleTitle><Pagination><StartPage>406</StartPage><EndPage>410</EndPage><MedlinePgn>406-10</MedlinePgn></Pagination><Abstract><AbstractText>Intestinal invagination is rather frequently associated with local tumors, adenovirus infections, and occasionally with Yersinia enterocolitica. However, in many cases the etiology is not known. We have studied 88 children with intestinal invagination in whom cellular cultures of Hep 2 and pulmonary fibroblasts of human embryo have been inoculated with a fecal sample. The clinical reports have been reviewed retrospectively. In 19 patients (21.59%) we obtained an adenovirus and in 12 patients (13.63%) we isolated enteroviruses. These results have been compared with a control group of 1,059 children of a comparable age and during the same period of time who were admitted because diagnoses other than intestinal invagination. All controls where subjected to viral investigation in feces following the same procedure. In 71 of controls (6.7%) there were adenovirus in feces and in 74 cases (6.98%) the culture evidenced enteroviruses. Group differences for adenovirus were statistically significant (p = 0.00000172), whereas infections for enteroviruses reached a small significance (p = 0.03892). Among the 18 patients with intestinal invagination in whom the cultures were positive for adenoviruses, 10 presented a recent high airway infection. In contrast, this infection was only observed in 3 out of the 12 patients with culture positive to enteroviruses. The etiology of intestinal invagination in a large number of patients remains to be established. There are many pathogenic intestinal viruses that might cause intestinal invagination but they may be unable to grow into cellular cultures.</AbstractText></Abstract><AuthorList CompleteYN="Y"><Author ValidYN="Y"><LastName>Calic&#xf3;</LastName><ForeName>I</ForeName><Initials>I</Initials><AffiliationInfo><Affiliation>Servicio de Microbiolog&#xed;a, Hospital Vall d'Hebron, Barcelona.</Affiliation></AffiliationInfo></Author><Author ValidYN="Y"><LastName>Bertr&#xe1;n Sangu&#xe9;s</LastName><ForeName>J M</ForeName><Initials>JM</Initials></Author><Author ValidYN="Y"><LastName>Elcuaz Romano</LastName><ForeName>R I</ForeName><Initials>RI</Initials></Author><Author ValidYN="Y"><LastName>Casal</LastName><ForeName>J</ForeName><Initials>J</Initials></Author><Author ValidYN="Y"><LastName>Su&#xf1;&#xe9; Gracia</LastName><ForeName>M J</ForeName><Initials>MJ</Initials></Author></AuthorList><Language>spa</Language><PublicationTypeList><PublicationType UI="D004740">English Abstract</PublicationType><PublicationType UI="D016428">Journal Article</PublicationType><PublicationType UI="D016454">Review</PublicationType></PublicationTypeList><VernacularTitle>Infecciones v&#xed;ricas asociadas a invaginaci&#xf3;n intestinal.</VernacularTitle></Article><MedlineJournalInfo><Country>Spain</Country><MedlineTA>Enferm Infecc Microbiol Clin</MedlineTA><NlmUniqueID>9104081</NlmUniqueID><ISSNLinking>0213-005X</ISSNLinking></MedlineJournalInfo><CitationSubset>IM</CitationSubset><MeshHeadingList><MeshHeading><DescriptorName UI="D000257" MajorTopicYN="N">Adenoviridae Infections</DescriptorName><QualifierName UI="Q000150" MajorTopicYN="N">complications</QualifierName><QualifierName UI="Q000453" MajorTopicYN="N">epidemiology</QualifierName></MeshHeading><MeshHeading><DescriptorName UI="D000260" MajorTopicYN="N">Adenoviruses, Human</DescriptorName><QualifierName UI="Q000302" MajorTopicYN="N">isolation &amp; purification</QualifierName></MeshHeading><MeshHeading><DescriptorName UI="D002460" MajorTopicYN="N">Cell Line</DescriptorName></MeshHeading><MeshHeading><DescriptorName UI="D002675" MajorTopicYN="N">Child, Preschool</DescriptorName></MeshHeading><MeshHeading><DescriptorName UI="D004770" MajorTopicYN="N">Enterovirus</DescriptorName><QualifierName UI="Q000302" MajorTopicYN="N">isolation &amp; purification</QualifierName></MeshHeading><MeshHeading><DescriptorName UI="D004769" MajorTopicYN="N">Enterovirus Infections</DescriptorName><QualifierName UI="Q000150" MajorTopicYN="N">complications</QualifierName><QualifierName UI="Q000453" MajorTopicYN="N">epidemiology</QualifierName></MeshHeading><MeshHeading><DescriptorName UI="D005260" MajorTopicYN="N">Female</DescriptorName></MeshHeading><MeshHeading><DescriptorName UI="D006801" MajorTopicYN="N">Humans</DescriptorName></MeshHeading><MeshHeading><DescriptorName UI="D007223" MajorTopicYN="N">Infant</DescriptorName></MeshHeading><MeshHeading><DescriptorName UI="D007443" MajorTopicYN="N">Intussusception</DescriptorName><QualifierName UI="Q000209" MajorTopicYN="Y">etiology</QualifierName><QualifierName UI="Q000382" MajorTopicYN="N">microbiology</QualifierName></MeshHeading><MeshHeading><DescriptorName UI="D008297" MajorTopicYN="N">Male</DescriptorName></MeshHeading><MeshHeading><DescriptorName UI="D012189" MajorTopicYN="N">Retrospective Studies</DescriptorName></MeshHeading><MeshHeading><DescriptorName UI="D012621" MajorTopicYN="N">Seasons</DescriptorName></MeshHeading><MeshHeading><DescriptorName UI="D014776" MajorTopicYN="N">Virus Cultivation</DescriptorName></MeshHeading><MeshHeading><DescriptorName UI="D014777" MajorTopicYN="N">Virus Diseases</DescriptorName><QualifierName UI="Q000150" MajorTopicYN="Y">complications</QualifierName><QualifierName UI="Q000453" MajorTopicYN="N">epidemiology</QualifierName></MeshHeading></MeshHeadingList><NumberOfReferences>10</NumberOfReferences></MedlineCitation><PubmedData><History><PubMedPubDate PubStatus="pubmed"><Year>1990</Year><Month>8</Month><Day>1</Day></PubMedPubDate><PubMedPubDate PubStatus="medline"><Year>1990</Year><Month>8</Month><Day>1</Day><Hour>0</Hour><Minute>1</Minute></PubMedPubDate><PubMedPubDate PubStatus="entrez"><Year>1990</Year><Month>8</Month><Day>1</Day><Hour>0</Hour><Minute>0</Minute></PubMedPubDate></History><PublicationStatus>ppublish</PublicationStatus><ArticleIdList><ArticleId IdType="pubmed">1967100</ArticleId></ArticleIdList></PubmedData></PubmedArticle></PubmedArticleSet>