<?xml version="1.0" ?>
<!DOCTYPE PubmedArticleSet PUBLIC "-//NLM//DTD PubMedArticle, 1st January 2024//EN" "https://dtd.nlm.nih.gov/ncbi/pubmed/out/pubmed_240101.dtd">
<PubmedArticleSet>
<PubmedArticle><MedlineCitation Status="MEDLINE" Owner="NLM" IndexingMethod="Automated"><PMID Version="1">35589587</PMID><DateCompleted><Year>2022</Year><Month>05</Month><Day>23</Day></DateCompleted><DateRevised><Year>2022</Year><Month>05</Month><Day>23</Day></DateRevised><Article PubModel="Print"><Journal><ISSN IssnType="Print">0254-6450</ISSN><JournalIssue CitedMedium="Print"><Volume>43</Volume><Issue>5</Issue><PubDate><Year>2022</Year><Month>May</Month><Day>10</Day></PubDate></JournalIssue><Title>Zhonghua liu xing bing xue za zhi = Zhonghua liuxingbingxue zazhi</Title><ISOAbbreviation>Zhonghua Liu Xing Bing Xue Za Zhi</ISOAbbreviation></Journal><ArticleTitle>[Etiology and epidemiology of hand, foot and mouth disease in China].</ArticleTitle><Pagination><StartPage>771</StartPage><EndPage>783</EndPage><MedlinePgn>771-783</MedlinePgn></Pagination><ELocationID EIdType="doi" ValidYN="Y">10.3760/cma.j.cn112338-20211012-00788</ELocationID><Abstract><AbstractText>Hand, foot and mouth disease (HFMD) has been widespread in the world, and caused fever, rashes and other clinical symptoms of children, and sometimes inducing respiratory failure, brainstem encephalitis, and other complications, even death. The disease is mainly caused by enterovirus 71 (EV-A71) and coxsackievirus 16 (CV-A16). Since 2013, the proportion of HFMD cases caused by other enteroriruses has gradually increased, causing severe and even fatal cases. This paper summarizes the research progress in the epidemiological and etiological characteristics of HFMD in China since 2008.</AbstractText></Abstract><AuthorList CompleteYN="Y"><Author ValidYN="Y"><LastName>Zhang</LastName><ForeName>J</ForeName><Initials>J</Initials><AffiliationInfo><Affiliation>Division of Infectious Disease Control and Prevention, Chinese Center for Disease Control and Prevention, Beijing 102206, China.</Affiliation></AffiliationInfo></Author><Author ValidYN="Y"><LastName>Li</LastName><ForeName>X H</ForeName><Initials>XH</Initials><AffiliationInfo><Affiliation>Integrated Traditional Chinese and Western Medicine Center, Beijing Youan Hospital of Capital Medical University, Beijing 100069, China.</Affiliation></AffiliationInfo></Author><Author ValidYN="Y"><LastName>Li</LastName><ForeName>X F</ForeName><Initials>XF</Initials><AffiliationInfo><Affiliation>Integrated Traditional Chinese and Western Medicine Center, Beijing Youan Hospital of Capital Medical University, Beijing 100069, China.</Affiliation></AffiliationInfo></Author><Author ValidYN="Y"><LastName>Shang</LastName><ForeName>Xiaofei</ForeName><Initials>X</Initials><AffiliationInfo><Affiliation>Integrated Traditional Chinese and Western Medicine Center, Beijing Youan Hospital of Capital Medical University, Beijing 100069, China.</Affiliation></AffiliationInfo></Author></AuthorList><Language>chi</Language><GrantList CompleteYN="Y"><Grant><GrantID>2017ZX10305501004</GrantID><Agency>National Science and Technology Major Project of China</Agency><Country/></Grant></GrantList><PublicationTypeList><PublicationType UI="D016428">Journal Article</PublicationType></PublicationTypeList></Article><MedlineJournalInfo><Country>China</Country><MedlineTA>Zhonghua Liu Xing Bing Xue Za Zhi</MedlineTA><NlmUniqueID>8208604</NlmUniqueID><ISSNLinking>0254-6450</ISSNLinking></MedlineJournalInfo><CitationSubset>IM</CitationSubset><MeshHeadingList><MeshHeading><DescriptorName UI="D002648" MajorTopicYN="N">Child</DescriptorName></MeshHeading><MeshHeading><DescriptorName UI="D002681" MajorTopicYN="N" Type="Geographic">China</DescriptorName><QualifierName UI="Q000453" MajorTopicYN="N">epidemiology</QualifierName></MeshHeading><MeshHeading><DescriptorName UI="D004660" MajorTopicYN="Y">Encephalitis</DescriptorName></MeshHeading><MeshHeading><DescriptorName UI="D004770" MajorTopicYN="Y">Enterovirus</DescriptorName></MeshHeading><MeshHeading><DescriptorName UI="D029821" MajorTopicYN="Y">Enterovirus A, Human</DescriptorName></MeshHeading><MeshHeading><DescriptorName UI="D006232" MajorTopicYN="Y">Hand, Foot and Mouth Disease</DescriptorName><QualifierName UI="Q000453" MajorTopicYN="N">epidemiology</QualifierName></MeshHeading><MeshHeading><DescriptorName UI="D006801" MajorTopicYN="N">Humans</DescriptorName></MeshHeading></MeshHeadingList><OtherAbstract Type="Publisher" Language="chi"><AbstractText>&#x624b;&#x8db3;&#x53e3;&#x75c5;&#x662f;&#x4e16;&#x754c;&#x8303;&#x56f4;&#x5e7f;&#x6cdb;&#x6d41;&#x884c;&#x7684;&#x4f20;&#x67d3;&#x75c5;&#xff0c;&#x591a;&#x53d1;&#x751f;&#x4e8e;5&#x5c81;&#x4ee5;&#x4e0b;&#x513f;&#x7ae5;&#xff0c;&#x53ef;&#x5f15;&#x8d77;&#x624b;&#x3001;&#x8db3;&#x3001;&#x53e3;&#x8154;&#x7b49;&#x90e8;&#x4f4d;&#x7684;&#x76ae;&#x75b9;&#x548c;&#x75b1;&#x75b9;&#xff0c;&#x90e8;&#x5206;&#x91cd;&#x75c7;&#x53ef;&#x5bfc;&#x81f4;&#x6b7b;&#x4ea1;&#xff0c;&#x4e25;&#x91cd;&#x5a01;&#x80c1;&#x513f;&#x7ae5;&#x5065;&#x5eb7;&#x3002;&#x80a0;&#x9053;&#x75c5;&#x6bd2;A&#x7ec4;71&#x578b;&#xff08;EV-A71&#xff09;&#x548c;&#x67ef;&#x8428;&#x5947;&#x75c5;&#x6bd2;A&#x7ec4;16&#x578b;&#xff08;CV-A16&#xff09;&#x7b49;EV&#x662f;&#x5f15;&#x8d77;&#x6211;&#x56fd;&#x624b;&#x8db3;&#x53e3;&#x75c5;&#x6301;&#x7eed;&#x6d41;&#x884c;&#x7684;&#x4e3b;&#x8981;&#x75c5;&#x56e0;&#x3002;2013&#x5e74;&#x4ee5;&#x540e;&#xff0c;&#x5176;&#x4ed6;EV&#x5728;&#x624b;&#x8db3;&#x53e3;&#x75c5;&#x75c5;&#x4f8b;&#x4e2d;&#x6240;&#x5360;&#x6bd4;&#x4f8b;&#x9010;&#x6e10;&#x589e;&#x591a;&#xff0c;&#x5f15;&#x8d77;&#x91cd;&#x75c7;&#x548c;&#x6b7b;&#x4ea1;&#x75c5;&#x4f8b;&#x3002;&#x672c;&#x6587;&#x5bf9;2008&#x5e74;&#x4ee5;&#x6765;&#x6211;&#x56fd;&#x624b;&#x8db3;&#x53e3;&#x75c5;&#x6d41;&#x884c;&#x75c5;&#x5b66;&#x548c;&#x75c5;&#x539f;&#x5b66;&#x7684;&#x4e3b;&#x8981;&#x7814;&#x7a76;&#x8fdb;&#x5c55;&#x8fdb;&#x884c;&#x7efc;&#x8ff0;&#x3002;.</AbstractText></OtherAbstract></MedlineCitation><PubmedData><History><PubMedPubDate PubStatus="entrez"><Year>2022</Year><Month>5</Month><Day>19</Day><Hour>22</Hour><Minute>14</Minute></PubMedPubDate><PubMedPubDate PubStatus="pubmed"><Year>2022</Year><Month>5</Month><Day>20</Day><Hour>6</Hour><Minute>0</Minute></PubMedPubDate><PubMedPubDate PubStatus="medline"><Year>2022</Year><Month>5</Month><Day>24</Day><Hour>6</Hour><Minute>0</Minute></PubMedPubDate></History><PublicationStatus>ppublish</PublicationStatus><ArticleIdList><ArticleId IdType="pubmed">35589587</ArticleId><ArticleId IdType="doi">10.3760/cma.j.cn112338-20211012-00788</ArticleId></ArticleIdList></PubmedData></PubmedArticle></PubmedArticleSet>